TableGeneration/__init__.py
TableGeneration/synthesize.py
TableGeneration/vis_gt.py
TableGeneration/TableGeneration/GenerateTable.py
TableGeneration/TableGeneration/Table.py
TableGeneration/TableGeneration/__init__.py
table_synthesis/.gitignore
table_synthesis/.pre-commit-config.yaml
table_synthesis/LICENSE.md
table_synthesis/__init__.py
table_synthesis/requirements.txt
table_synthesis/synthesize.py
table_synthesis/vis_gt.py
table_synthesis/.git/FETCH_HEAD
table_synthesis/.git/HEAD
table_synthesis/.git/config
table_synthesis/.git/description
table_synthesis/.git/index
table_synthesis/.git/packed-refs
table_synthesis/.git/hooks/applypatch-msg.sample
table_synthesis/.git/hooks/commit-msg.sample
table_synthesis/.git/hooks/fsmonitor-watchman.sample
table_synthesis/.git/hooks/post-update.sample
table_synthesis/.git/hooks/pre-applypatch.sample
table_synthesis/.git/hooks/pre-commit.sample
table_synthesis/.git/hooks/pre-merge-commit.sample
table_synthesis/.git/hooks/pre-push.sample
table_synthesis/.git/hooks/pre-rebase.sample
table_synthesis/.git/hooks/pre-receive.sample
table_synthesis/.git/hooks/prepare-commit-msg.sample
table_synthesis/.git/hooks/push-to-checkout.sample
table_synthesis/.git/hooks/update.sample
table_synthesis/.git/info/exclude
table_synthesis/.git/logs/HEAD
table_synthesis/.git/logs/refs/heads/main
table_synthesis/.git/logs/refs/remotes/origin/HEAD
table_synthesis/.git/objects/pack/pack-1aa0926effa30c36a74509bd1aa83df7ba052033.idx
table_synthesis/.git/objects/pack/pack-1aa0926effa30c36a74509bd1aa83df7ba052033.pack
table_synthesis/.git/refs/heads/main
table_synthesis/.git/refs/remotes/origin/HEAD
table_synthesis/TableGeneration/GenerateTable.py
table_synthesis/TableGeneration/Table.py
table_synthesis/TableGeneration/__init__.py
table_synthesis/TableGeneration/__pycache__/GenerateTable.cpython-310.pyc
table_synthesis/TableGeneration/__pycache__/Table.cpython-310.pyc
table_synthesis/TableGeneration/__pycache__/__init__.cpython-310.pyc
table_synthesis-1.0.0.dist-info/METADATA
table_synthesis-1.0.0.dist-info/WHEEL
table_synthesis-1.0.0.dist-info/top_level.txt
table_synthesis-1.0.0.dist-info/RECORD
