Metadata-Version: 2.1
Name: table-synthesis
Version: 1.0.0
Summary: Table Image Synthesis
Classifier: Programming Language :: Python :: 3
Classifier: License :: OSI Approved :: MIT License
Classifier: Operating System :: OS Independent
Requires-Python: >=3.8
Requires-Dist: beautifulsoup4 (==4.11.1)
Requires-Dist: numpy (==1.24.4)
Requires-Dist: opencv-contrib-python (==4.6.0.66)
Requires-Dist: opencv-python (==4.7.0.68)
Requires-Dist: opencv-python-headless (==4.8.1.78)
Requires-Dist: Pillow (==10.1.0)
Requires-Dist: selenium (==3.8.1)
Requires-Dist: tqdm (==4.65.0)
